msl/examples/odt/PM5544_with_non-PAL_signals.png
msl/examples/odt/Sweden_TV1_colour_1969.png
msl/examples/odt/example_msl-odt_append.py
msl/examples/odt/example_msl-odt_figures.py
msl/examples/odt/example_msl-odt_introduction.py
msl/examples/odt/example_msl-odt_lists.py
msl/examples/odt/example_msl-odt_math.py
msl/examples/odt/example_msl-odt_readme.odt
msl/examples/odt/example_msl-odt_tables.py
msl/odt/__init__.py
msl/odt/_version.py
msl/odt/odt.py
msl_odt-1.0.dist-info/METADATA
msl_odt-1.0.dist-info/WHEEL
msl_odt-1.0.dist-info/licenses/LICENSE.txt
msl_odt-1.0.dist-info/RECORD
