Metadata-Version: 2.4
Name: msl-odt
Version: 1.0
Summary: Write Open Document Foundation documents with Python.
Project-URL: Changelog, https://mslnz.github.io/msl-odt/about/release-notes/
Project-URL: Documentation, https://mslnz.github.io/msl-odt/
Project-URL: Homepage, https://mslnz.github.io/msl-odt/
Project-URL: Issues, https://github.com/MSLNZ/msl-odt/issues
Project-URL: Source, https://github.com/MSLNZ/msl-odt
Author-email: Measurement Standards Laboratory of New Zealand <info@measurement.govt.nz>
Maintainer-email: Adam Dunford <adam.dunford@measurement.govt.nz>
License: MIT License
License-File: LICENSE.txt
Keywords: .odt,MSL,Open Document Foundation,Open Office
Classifier: Development Status :: 4 - Beta
Classifier: Intended Audience :: Developers
Classifier: Intended Audience :: Science/Research
Classifier: License :: OSI Approved :: MIT License
Classifier: Operating System :: OS Independent
Classifier: Programming Language :: Python
Classifier: Programming Language :: Python :: 3
Classifier: Programming Language :: Python :: 3.8
Classifier: Programming Language :: Python :: 3.9
Classifier: Programming Language :: Python :: 3.10
Classifier: Programming Language :: Python :: 3.11
Classifier: Programming Language :: Python :: 3.12
Classifier: Programming Language :: Python :: 3.13
Classifier: Topic :: Scientific/Engineering
Classifier: Topic :: Software Development
Requires-Python: >=3.8
Requires-Dist: odfpy
Provides-Extra: dev
Requires-Dist: black; extra == 'dev'
Requires-Dist: markdown; extra == 'dev'
Requires-Dist: mkdocs; extra == 'dev'
Requires-Dist: mkdocs-material; extra == 'dev'
Requires-Dist: mkdocstrings-python; extra == 'dev'
Requires-Dist: pymdown-extensions; extra == 'dev'
Requires-Dist: pytest; extra == 'dev'
Provides-Extra: docs
Requires-Dist: black; extra == 'docs'
Requires-Dist: markdown; extra == 'docs'
Requires-Dist: mkdocs; extra == 'docs'
Requires-Dist: mkdocs-material; extra == 'docs'
Requires-Dist: mkdocstrings-python; extra == 'docs'
Requires-Dist: pymdown-extensions; extra == 'docs'
Provides-Extra: tests
Requires-Dist: pytest; extra == 'tests'
